LICENSE
MANIFEST.in
README.rst
setup.py
btc_dev_tools.egg-info/PKG-INFO
btc_dev_tools.egg-info/SOURCES.txt
btc_dev_tools.egg-info/dependency_links.txt
btc_dev_tools.egg-info/top_level.txt
dev_tools/__init__.py
dev_tools/apps.py
dev_tools/utils.py
dev_tools/db/__init__.py
dev_tools/db/transactions.py
dev_tools/forms/mixins.py
dev_tools/meta/__init__.py
dev_tools/meta/metaclasses.py
dev_tools/template/__init__.py
dev_tools/template/components.py
dev_tools/template/mixins.py
dev_tools/template/utils.py
dev_tools/templatetags/__init__.py
dev_tools/templatetags/dev_tools.py